MANIFEST.in
README.rst
setup.cfg
setup.py
passman/JSON.py
passman/__init__.py
passman/__main__.py
passman/commandline.py
passman/database.py
passman/encryption.py
passman/functions.py
passman/login.py
passman/menu.py
passman/offlinemenu.py
passman.egg-info/PKG-INFO
passman.egg-info/SOURCES.txt
passman.egg-info/dependency_links.txt
passman.egg-info/entry_points.txt
passman.egg-info/requires.txt
passman.egg-info/top_level.txt