Metadata-Version: 1.1
Name: passman
Version: 1.1.7
Summary: A terminal-based password manager
Home-page: https://github.com/regexpressyourself/passman
Author: Sam Messina
Author-email: samuel.messina@gmail.com
License: MIT
Download-URL: https://github.com/regexpressyourself/passman/1.0.tar.gz
Keywords: password,manager,terminal
Platform: UNKNOWN
